thumbor_libs_blackhand/loaders/__init__.py
thumbor_libs_blackhand/loaders/mongodb_loader.py
thumbor_libs_blackhand/loaders/spec_http_or_specb_loader.py
thumbor_libs_blackhand/loaders/specb_file_fallback_file_loader.py
thumbor_libs_blackhand/metrics/__init__.py
thumbor_libs_blackhand/mongodb/pool_result_storage.py
thumbor_libs_blackhand/result_storages/__init__.py
thumbor_libs_blackhand/result_storages/hybrid_result_storage.py
thumbor_libs_blackhand/result_storages/mongodb_result_storage_v3.py
thumbor_libs_blackhand/result_storages/mongodb_result_storage_v4.py
thumbor_libs_blackhand/result_storages/mongodb_result_storage_v5.py
thumbor_libs_blackhand/storages/__init__.py
thumbor_libs_blackhand/storages/mongodb_webp_storage.py
thumbor_libs_blackhand/url_signers/__init__.py
thumbor_libs_blackhand/url_signers/base64_hmac_sha1_trim.py
thumbor_libs_blackhand-0.5.0.dist-info/LICENSE
thumbor_libs_blackhand-0.5.0.dist-info/METADATA
thumbor_libs_blackhand-0.5.0.dist-info/WHEEL
thumbor_libs_blackhand-0.5.0.dist-info/top_level.txt
thumbor_libs_blackhand-0.5.0.dist-info/RECORD
